django_safe_project-0.0.6.dist-info/METADATA
django_safe_project-0.0.6.dist-info/entry_points.txt
django_safe_project-0.0.6.dist-info/metadata.json
django_safe_project-0.0.6.dist-info/DESCRIPTION.rst
django_safe_project-0.0.6.dist-info/WHEEL
django_safe_project-0.0.6.dist-info/RECORD
django_safe_project-0.0.6.dist-info/top_level.txt
django_safe_project-0.0.6.data/scripts/startproject.py
django_safe_project/__init__.py
django_safe_project/safe_settings.py
django_safe_project/template.py
