Metadata-Version: 2.0
Name: django-safe-project
Version: 0.0.6
Summary: Start Django projects with sensitive data outside of the global settings module
Home-page: https://github.com/nocarryr/django-safe-project
Author: Matthew Reid
Author-email: matt@nomadic-recording.com
License: MIT
Keywords: django
Platform: UNKNOWN
Classifier: Development Status :: 3 - Alpha
Classifier: Environment :: Web Environment
Classifier: Framework :: Django
Classifier: Intended Audience :: Developers
Classifier: License :: OSI Approved :: MIT License
Classifier: Operating System :: OS Independent
Classifier: Programming Language :: Python
Classifier: Topic :: Security
Classifier: Programming Language :: Python :: 2
Classifier: Programming Language :: Python :: 2.7
Classifier: Programming Language :: Python :: 3
Classifier: Programming Language :: Python :: 3.4
